[{"component":"general","errorCode":"6275","formattedMessage":"ParserError: Source \"ERC721.sol\" not found: File import callback not supported\n --> CosmoNuts.sol:4:1:\n  |\n4 | import \"./ERC721.sol\";\n  | ^^^^^^^^^^^^^^^^^^^^^^\n\n","message":"Source \"ERC721.sol\" not found: File import callback not supported","severity":"error","sourceLocation":{"end":79,"file":"CosmoNuts.sol","start":57},"type":"ParserError"},{"component":"general","errorCode":"6275","formattedMessage":"ParserError: Source \"extensions/ERC721Enumerable\" not found: File import callback not supported\n --> CosmoNuts.sol:5:1:\n  |\n5 | import \"../extensions/ERC721Enumerable\";\n  | ^^^^^^^^^^^^^^^^^^^^^^^^^^^^^^^^^^^^^^^^\n\n","message":"Source \"extensions/ERC721Enumerable\" not found: File import callback not supported","severity":"error","sourceLocation":{"end":120,"file":"CosmoNuts.sol","start":80},"type":"ParserError"},{"component":"general","errorCode":"6275","formattedMessage":"ParserError: Source \"extensions/ERC721URIStorage.sol\" not found: File import callback not supported\n --> CosmoNuts.sol:6:1:\n  |\n6 | import \"../extensions/ERC721URIStorage.sol\";\n  | ^^^^^^^^^^^^^^^^^^^^^^^^^^^^^^^^^^^^^^^^^^^^\n\n","message":"Source \"extensions/ERC721URIStorage.sol\" not found: File import callback not supported","severity":"error","sourceLocation":{"end":165,"file":"CosmoNuts.sol","start":121},"type":"ParserError"},{"component":"general","errorCode":"6275","formattedMessage":"ParserError: Source \"access/Ownable.sol\" not found: File import callback not supported\n --> CosmoNuts.sol:7:1:\n  |\n7 | import \"../access/Ownable.sol\";\n  | ^^^^^^^^^^^^^^^^^^^^^^^^^^^^^^^\n\n","message":"Source \"access/Ownable.sol\" not found: File import callback not supported","severity":"error","sourceLocation":{"end":197,"file":"CosmoNuts.sol","start":166},"type":"ParserError"}]
